{
  "name": "images/S90G7i4JlSaXttI4LecUFrfAEZtM/1703169252885",
  "bucket": "cs554-final-project-8094e.appspot.com",
  "metageneration": 1,
  "generation": 1703169252896,
  "contentType": "image/png",
  "storageClass": "STANDARD",
  "contentDisposition": "inline",
  "downloadTokens": [
    "d8fc8691-18be-4c19-a330-c78f53f266c2"
  ],
  "etag": "0aiF/xaYLluAtb66Wh10Q0NileM",
  "customMetadata": {},
  "timeCreated": "2023-12-21T14:34:12.896Z",
  "updated": "2023-12-21T14:34:12.896Z",
  "size": 21592,
  "md5Hash": "dXACUytkK1T8GHZPrPkjbw==",
  "crc32c": "4264258882"
}